pkradio/__init__.py
pkradio/pkradio.py
pkradio/stations.json
pkradio-0.3.dist-info/METADATA
pkradio-0.3.dist-info/WHEEL
pkradio-0.3.dist-info/top_level.txt
pkradio-0.3.dist-info/RECORD
