Metadata-Version: 2.1
Name: pkradio
Version: 0.3
Summary: Pakistani radio listener for a list stations, that'll hopefully keep growing.
Author: siphr
Author-email: pypi@techtum.dev
Project-URL: Homepage, https://www.techtum.dev/work-pkradio-220409.html
Project-URL: Source, https://github.com/siphr/pkradio
Project-URL: Tracker, https://github.com/siphr/pkradio/issues
Keywords: pakistani,urdu,sindhi,radio,internet,live
Platform: any
